{
  "graph": {
    "directed": true,
    "nodes": {
      "os0": {
        "label": "os0",
        "metadata": {
          "basename": "os",
          "exclusive": false,
          "id": 0,
          "name": "os0",
          "paths": {
            "containment": "/os0"
          },
          "size": 1,
          "type": "os",
          "uniq_id": 0
        }
      },
      "os1": {
        "label": "os1",
        "metadata": {
          "basename": "os.full=ubuntu22.04",
          "exclusive": true,
          "id": 1,
          "name": "os.full=ubuntu22.040",
          "paths": {
            "containment": "/os1/os.full=ubuntu22.040"
          },
          "size": 1,
          "type": "os.full=ubuntu22.04",
          "uniq_id": 1
        }
      }
    },
    "edges": [
      {
        "source": "2",
        "target": "os1",
        "relation": "contains"
      },
      {
        "source": "os1",
        "target": "2",
        "relation": "in"
      },
      {
        "source": "14",
        "target": "os1",
        "relation": "contains"
      },
      {
        "source": "os1",
        "target": "14",
        "relation": "in"
      },
      {
        "source": "10",
        "target": "os1",
        "relation": "contains"
      },
      {
        "source": "os1",
        "target": "10",
        "relation": "in"
      },
      {
        "source": "5",
        "target": "os1",
        "relation": "contains"
      },
      {
        "source": "os1",
        "target": "6",
        "relation": "in"
      }
    ]
  }
}